{
    "state_changes": [
        {
            "task_id": "e3b2253b-0b92-491d-b8d2-df7cf8344b90",
            "task_name": "nwchem_bin",
            "next_state": "PENDING",
            "timestamp": 1644852572
        },
        {
            "task_id": "e3b2253b-0b92-491d-b8d2-df7cf8344b90",
            "task_name": "nwchem_bin",
            "next_state": "RUNNING",
            "timestamp": 1644852577
        },
        {
            "task_id": "e3b2253b-0b92-491d-b8d2-df7cf8344b90",
            "task_name": "nwchem_bin",
            "next_state": "COMPLETED",
            "timestamp": 1644852662
        }
    ],
    "scheduling_results": []
}